phizz/__init__.py
phizz/__main__.py
phizz/cli.py
phizz/log.py
phizz/database/__init__.py
phizz/database/build.py
phizz/database/constants.py
phizz/database/create_database.py
phizz/database/populate_database.py
phizz/resources/.DS_Store
phizz/resources/ALL_SOURCES_ALL_FREQUENCIES_diseases_to_genes_to_phenotypes.txt.gz
phizz/resources/ALL_SOURCES_ALL_FREQUENCIES_phenotype_to_genes.txt.gz
phizz/resources/HI_scores.txt
phizz/resources/HI_scores.txt.gz
phizz/resources/config.ini
phizz/resources/forweb_cleaned_exac_r03_march16_z_data_pLI.txt.gz
phizz/resources/genes.db
phizz/resources/genes_37.txt.gz
phizz/resources/phenotypes.txt.gz
phizz/resources/phizz.db
phizz/resources/schema.sql
phizz/resources/transcripts_37.txt.gz
phizz/utils/__init__.py
phizz/utils/build_gene_trees.py
phizz/utils/parse_resource.py
phizz/utils/prepare_files.py
phizz/utils/queries.py
phizz-0.2.3.dist-info/DESCRIPTION.rst
phizz-0.2.3.dist-info/METADATA
phizz-0.2.3.dist-info/RECORD
phizz-0.2.3.dist-info/WHEEL
phizz-0.2.3.dist-info/entry_points.txt
phizz-0.2.3.dist-info/metadata.json
phizz-0.2.3.dist-info/top_level.txt
