Metadata-Version: 1.1
Name: phizz
Version: 0.2.3
Summary: Tool to query hpo database and some other sources
Home-page: https://github.com/moonso/query_hpo
Author: Måns Magnusson
Author-email: mans.magnusson@scilifelab.com
License: MIT
Keywords: hpo omim hgnc
Platform: UNKNOWN
Classifier: Development Status :: 3 - Alpha
Classifier: Intended Audience :: Developers
Classifier: Topic :: Software Development
Classifier: License :: OSI Approved :: MIT License
Classifier: Programming Language :: Python :: 2
Classifier: Programming Language :: Python :: 2.7
Classifier: Programming Language :: Python :: 3
Classifier: Programming Language :: Python :: 3.3
Classifier: Programming Language :: Python :: 3.4
Classifier: Environment :: Console
